{
  "schema_version": "1.4",
  "project_positioning": {
    "research_question": "When does a more sophisticated classical optimizer justify its runtime, shot, queue, and mitigation cost for constrained QAOA portfolio optimization?",
    "what_this_project_is": "A hardware-aware benchmark platform for constrained QAOA portfolio optimization rather than a one-off demo or toy VQE script.",
    "technical_contributions": [
      "Multi-regime synthetic portfolio generator with exact feasible references on small instances.",
      "Constraint-aware QAOA benchmark with CVaR-style objectives, feasibility tracking, and valid-ratio histories.",
      "Strict runtime accounting across objective calls, effective shots, transpilation time, execution time, queue latency, and estimated billed QPU cost.",
      "Fair optimizer comparison across a classical Markowitz baseline, Random Search, SPSA, and Bayesian Optimization with periodic-safe surrogate handling for QAOA angles.",
      "Per-instance QUBO structure diagnostics including constraint hardness and simple spectral-profile summaries."
    ],
    "why_it_is_interesting": "It lets the user study when sophisticated classical search is actually worth its real hybrid-loop overhead, instead of assuming better optimization always means better practical performance.",
    "current_run_context": {
      "regime": "baseline",
      "execution_mode": "fast_simulator",
      "noise_model": "depolarizing",
      "mixer_type": "xy",
      "p_layers": 2
    }
  },
  "config": {
    "n_assets": 8,
    "budget": 3,
    "p_layers": 2,
    "risk_aversion": 0.6,
    "evaluation_budget": 12,
    "n_init_points": 4,
    "shots": 2048,
    "cvar_alpha": 0.1,
    "invalid_penalty": 50.0,
    "seed": 1,
    "output_prefix": "results/multi_regime_suite/shot_budget/shots_2048_seed_1",
    "regime": "baseline",
    "execution_mode": "fast_simulator",
    "backend_name": "aer_simulator",
    "execution_billing_mode": "job",
    "qpu_billing_basis": "total",
    "qpu_pricing_tier": "custom",
    "qpu_price_per_second_usd": 0.0,
    "job_queue_latency_seconds": 2.0,
    "transpile_optimization_level": 1,
    "transpile_topology": "auto",
    "routing_method": "sabre",
    "basis_gates": [],
    "seed_transpiler": 42,
    "calibration_aware_routing": true,
    "mock_edge_fidelity_sigma": 0.003,
    "mock_cnot_error_mean": 0.01,
    "noise_model": "depolarizing",
    "depolarizing_strength_1q": 0.001,
    "depolarizing_strength_2q": 0.01,
    "t1": 0.0001,
    "t2": 8e-05,
    "gate_time_1q": 5e-08,
    "gate_time_2q": 3e-07,
    "measurement_error": 0.01,
    "measurement_mitigation": true,
    "measurement_mitigation_max_bits": 12,
    "resilience_level": 0,
    "zne_mitigation": false,
    "zne_noise_factors": [
      1,
      3,
      5
    ],
    "twirling": false,
    "twirling_randomizations": 1,
    "qubo_penalty_multiplier": 2.0,
    "mixer_type": "xy",
    "penalty_validation_max_assets": 14,
    "penalty_validation_max_tries": 8,
    "exact_reference_max_assets": 14,
    "dicke_init_max_assets": 12,
    "bo_acquisition": "ucb",
    "bo_trust_region": true,
    "bo_target": "raw",
    "bo_feasibility_weight": 25.0,
    "bo_max_gp_dim": 16,
    "bo_high_dim_strategy": "random_embedding",
    "periodic_parameter_wrap": true,
    "bootstrap_resamples": 500,
    "save_individual_runs": true
  },
  "regime_characteristics": {
    "regime": "baseline",
    "n_assets": 8,
    "budget": 3,
    "shots": 2048,
    "p_layers": 2,
    "execution_mode": "fast_simulator",
    "execution_billing_mode": "job",
    "job_queue_latency_seconds": 2.0,
    "noise_model": "depolarizing",
    "measurement_mitigation": true,
    "zne_mitigation": false,
    "twirling": false,
    "resilience_level": 0,
    "transpile_topology": "auto",
    "routing_method": "sabre",
    "seed_transpiler": 42,
    "calibration_aware_routing": true,
    "bo_max_gp_dim": 16,
    "bo_high_dim_strategy": "random_embedding",
    "periodic_parameter_wrap": true,
    "qpu_pricing_tier": "custom",
    "qpu_price_per_second_usd": 0.0,
    "qpu_billing_basis": "total"
  },
  "exact_feasible_energy": -0.5085661952267606,
  "exact_reference_available": true,
  "exact_reference_warning": null,
  "qubo_profile": {
    "condition_number": 3.5184283315658447,
    "spectral_gap": 0.05411730504436585,
    "energy_gap_to_infeasible": -0.3839284411878108,
    "ground_state_participation_ratio": 1.0,
    "constraint_hardness": 0.21875
  },
  "empirical_reference": -0.5085661952267606,
  "methods": {
    "classical_markowitz": {
      "method": "classical_markowitz",
      "best_objective": -0.5085661952267606,
      "best_raw_objective": -0.5085661952267606,
      "best_valid_energy": -0.5085661952267606,
      "best_valid_ratio": 1.0,
      "feasible_hit_rate": 1.0,
      "mean_objective_variance": 0.0,
      "mean_approx_gap": 0.0,
      "objective_history": [
        -0.5085661952267606
      ],
      "raw_objective_history": [
        -0.5085661952267606
      ],
      "best_valid_history": [
        -0.5085661952267606
      ],
      "valid_ratio_history": [
        1.0
      ],
      "feasible_hit_history": [
        1.0
      ],
      "variance_history": [
        0.0
      ],
      "approx_gap_history": [
        0.0
      ],
      "elapsed_seconds": 0.00014029200247023255,
      "total_objective_calls": 1,
      "timing_totals": {
        "classical_overhead_seconds": 0.00014029200247023255,
        "circuit_construction_seconds": 0.0,
        "transpilation_seconds": 0.0,
        "execution_seconds": 0.0,
        "mitigation_seconds": 0.0,
        "queue_latency_seconds": 0.0,
        "total_seconds": 0.00014029200247023255
      },
      "total_effective_shots": 0.0,
      "total_estimated_billed_seconds": 0.0,
      "total_estimated_qpu_cost_usd": 0.0,
      "best_params": [
        0.0,
        1.0,
        0.0,
        1.0,
        0.0,
        0.0,
        1.0,
        0.0
      ],
      "evaluation_records": [
        {
          "evaluation_index": 1,
          "params": [
            0.0,
            1.0,
            0.0,
            1.0,
            0.0,
            0.0,
            1.0,
            0.0
          ],
          "objective": -0.5085661952267606,
          "raw_objective": -0.5085661952267606,
          "variance": 0.0,
          "observation_noise_variance": 1e-12,
          "best_valid_energy": -0.5085661952267606,
          "valid_ratio": 1.0,
          "feasible_hit": true,
          "approx_gap": 0.0,
          "timing": {
            "classical_overhead_seconds": 0.00014029200247023255,
            "circuit_construction_seconds": 0.0,
            "transpilation_seconds": 0.0,
            "execution_seconds": 0.0,
            "mitigation_seconds": 0.0,
            "queue_latency_seconds": 0.0,
            "total_seconds": 0.00014029200247023255
          },
          "backend_stats": {
            "backend_name": "classical_exact_enumeration",
            "initial_state_strategy": "uniform_superposition",
            "simulator_seed": null,
            "zne_simulator_seeds": [],
            "transpiled_depth": 0,
            "transpiled_size": 0,
            "two_qubit_gate_count": 0,
            "swap_gate_count": 0,
            "shot_multiplier": 1.0,
            "effective_shots": 0.0,
            "transpile_topology": "all_to_all",
            "basis_gates": [],
            "routing_method": "sabre",
            "seed_transpiler": null,
            "execution_billing_mode": "classical",
            "calibration_aware_routing": false,
            "mean_mock_cnot_error": 0.0,
            "max_mock_cnot_error": 0.0,
            "estimated_swap_risk_penalty": 0.0,
            "estimated_billed_seconds": 0.0,
            "estimated_qpu_cost_usd": 0.0
          }
        }
      ]
    },
    "random": {
      "method": "random",
      "best_objective": -0.4377720628164539,
      "best_raw_objective": -0.4377720628164539,
      "best_valid_energy": -0.5085661952267606,
      "best_valid_ratio": 0.34228515625,
      "feasible_hit_rate": 1.0,
      "mean_objective_variance": 0.0011782299256836576,
      "mean_approx_gap": 0.0,
      "objective_history": [
        -0.4150443520140228,
        -0.42457769723723254,
        -0.4377720628164539,
        -0.4377720628164539,
        -0.4377720628164539,
        -0.4377720628164539,
        -0.4377720628164539,
        -0.4377720628164539,
        -0.4377720628164539,
        -0.4377720628164539,
        -0.4377720628164539,
        -0.4377720628164539
      ],
      "raw_objective_history": [
        -0.4150443520140228,
        -0.42457769723723254,
        -0.4377720628164539,
        -0.4377720628164539,
        -0.4377720628164539,
        -0.4377720628164539,
        -0.4377720628164539,
        -0.4377720628164539,
        -0.4377720628164539,
        -0.4377720628164539,
        -0.4377720628164539,
        -0.4377720628164539
      ],
      "best_valid_history": [
        -0.5085661952267606,
        -0.5085661952267606,
        -0.5085661952267606,
        -0.5085661952267606,
        -0.5085661952267606,
        -0.5085661952267606,
        -0.5085661952267606,
        -0.5085661952267606,
        -0.5085661952267606,
        -0.5085661952267606,
        -0.5085661952267606,
        -0.5085661952267606
      ],
      "valid_ratio_history": [
        0.33056640625,
        0.34130859375,
        0.341796875,
        0.322265625,
        0.322265625,
        0.31201171875,
        0.34228515625,
        0.32666015625,
        0.3203125,
        0.32373046875,
        0.31689453125,
        0.318359375
      ],
      "feasible_hit_history": [
        1.0,
        1.0,
        1.0,
        1.0,
        1.0,
        1.0,
        1.0,
        1.0,
        1.0,
        1.0,
        1.0,
        1.0
      ],
      "variance_history": [
        0.0009011157358988775,
        0.0007399618394624552,
        0.0012603083508991586,
        0.0012417586822512372,
        0.0010236560793829008,
        0.0012658906438313966,
        0.0014495341377636084,
        0.0008195757605903298,
        0.0013458390150732913,
        0.001168448306909653,
        0.001869763846459177,
        0.0010529067096818057
      ],
      "approx_gap_history": [
        0.0,
        0.0,
        0.0,
        0.0,
        0.0,
        0.0,
        0.0,
        0.0,
        0.0,
        0.0,
        0.0,
        0.0
      ],
      "elapsed_seconds": 0.0690321669972036,
      "total_objective_calls": 12,
      "timing_totals": {
        "classical_overhead_seconds": 0.06887949899100931,
        "circuit_construction_seconds": 0.0,
        "transpilation_seconds": 0.0,
        "execution_seconds": 0.05406912599573843,
        "mitigation_seconds": 0.00235050300398143,
        "queue_latency_seconds": 24.0,
        "total_seconds": 24.12529970698961
      },
      "total_effective_shots": 30720.0,
      "total_estimated_billed_seconds": 24.0564202079986,
      "total_estimated_qpu_cost_usd": 0.0,
      "best_params": [
        6.071691088207557,
        3.1002148310054327,
        4.984028823269737,
        2.9386680887334586
      ],
      "evaluation_records": [
        {
          "evaluation_index": 1,
          "params": [
            2.656008658815972,
            1.8519753475192797,
            0.15387946498917343,
            2.115736633967084
          ],
          "objective": -0.4150443520140228,
          "raw_objective": -0.4150443520140228,
          "variance": 0.0009011157358988775,
          "observation_noise_variance": 4.399979179193738e-06,
          "best_valid_energy": -0.5085661952267606,
          "valid_ratio": 0.33056640625,
          "feasible_hit": true,
          "approx_gap": 0.0,
          "timing": {
            "classical_overhead_seconds": 0.005920916999457404,
            "circuit_construction_seconds": 0.0,
            "transpilation_seconds": 0.0,
            "execution_seconds": 0.004585000002407469,
            "mitigation_seconds": 0.0002392919996054843,
            "queue_latency_seconds": 2.0,
            "total_seconds": 2.0107452500014915
          },
          "backend_stats": {
            "backend_name": "fast_simulator",
            "initial_state_strategy": "dicke",
            "simulator_seed": null,
            "zne_simulator_seeds": [],
            "transpiled_depth": 0,
            "transpiled_size": 0,
            "two_qubit_gate_count": 0,
            "swap_gate_count": 0,
            "shot_multiplier": 1.25,
            "effective_shots": 2560.0,
            "transpile_topology": "analytical_statevector",
            "basis_gates": [],
            "routing_method": "sabre",
            "seed_transpiler": 42,
            "execution_billing_mode": "job",
            "calibration_aware_routing": true,
            "mean_mock_cnot_error": 0.0,
            "max_mock_cnot_error": 0.0,
            "estimated_swap_risk_penalty": 0.0,
            "estimated_billed_seconds": 2.004824333002034,
            "estimated_qpu_cost_usd": 0.0
          }
        },
        {
          "evaluation_index": 2,
          "params": [
            2.8165796224599475,
            1.1005867485875347,
            3.7130834592296633,
            2.4858864996819277
          ],
          "objective": -0.42457769723723254,
          "raw_objective": -0.42457769723723254,
          "variance": 0.0007399618394624552,
          "observation_noise_variance": 3.6130949192502695e-06,
          "best_valid_energy": -0.5085661952267606,
          "valid_ratio": 0.34130859375,
          "feasible_hit": true,
          "approx_gap": 0.0,
          "timing": {
            "classical_overhead_seconds": 0.0057603329987614416,
            "circuit_construction_seconds": 0.0,
            "transpilation_seconds": 0.0,
            "execution_seconds": 0.004522499999438878,
            "mitigation_seconds": 0.00019987500127172098,
            "queue_latency_seconds": 2.0,
            "total_seconds": 2.010482748999493
          },
          "backend_stats": {
            "backend_name": "fast_simulator",
            "initial_state_strategy": "dicke",
            "simulator_seed": null,
            "zne_simulator_seeds": [],
            "transpiled_depth": 0,
            "transpiled_size": 0,
            "two_qubit_gate_count": 0,
            "swap_gate_count": 0,
            "shot_multiplier": 1.25,
            "effective_shots": 2560.0,
            "transpile_topology": "analytical_statevector",
            "basis_gates": [],
            "routing_method": "sabre",
            "seed_transpiler": 42,
            "execution_billing_mode": "job",
            "calibration_aware_routing": true,
            "mean_mock_cnot_error": 0.0,
            "max_mock_cnot_error": 0.0,
            "estimated_swap_risk_penalty": 0.0,
            "estimated_billed_seconds": 2.0047224160007318,
            "estimated_qpu_cost_usd": 0.0
          }
        },
        {
          "evaluation_index": 3,
          "params": [
            6.071691088207557,
            3.1002148310054327,
            4.984028823269737,
            2.9386680887334586
          ],
          "objective": -0.4377720628164539,
          "raw_objective": -0.4377720628164539,
          "variance": 0.0012603083508991586,
          "observation_noise_variance": 6.153849369624798e-06,
          "best_valid_energy": -0.5085661952267606,
          "valid_ratio": 0.341796875,
          "feasible_hit": true,
          "approx_gap": 0.0,
          "timing": {
            "classical_overhead_seconds": 0.005746416994952597,
            "circuit_construction_seconds": 0.0,
            "transpilation_seconds": 0.0,
            "execution_seconds": 0.004520417001913302,
            "mitigation_seconds": 0.0001996669961954467,
            "queue_latency_seconds": 2.0,
            "total_seconds": 2.0104665419930825
          },
          "backend_stats": {
            "backend_name": "fast_simulator",
            "initial_state_strategy": "dicke",
            "simulator_seed": null,
            "zne_simulator_seeds": [],
            "transpiled_depth": 0,
            "transpiled_size": 0,
            "two_qubit_gate_count": 0,
            "swap_gate_count": 0,
            "shot_multiplier": 1.25,
            "effective_shots": 2560.0,
            "transpile_topology": "analytical_statevector",
            "basis_gates": [],
            "routing_method": "sabre",
            "seed_transpiler": 42,
            "execution_billing_mode": "job",
            "calibration_aware_routing": true,
            "mean_mock_cnot_error": 0.0,
            "max_mock_cnot_error": 0.0,
            "estimated_swap_risk_penalty": 0.0,
            "estimated_billed_seconds": 2.00472012499813,
            "estimated_qpu_cost_usd": 0.0
          }
        },
        {
          "evaluation_index": 4,
          "params": [
            1.6946619253661208,
            0.47438992172232586,
            4.0945658682996475,
            0.8364329083530003
          ],
          "objective": -0.3921265264683287,
          "raw_objective": -0.3921265264683287,
          "variance": 0.0012417586822512372,
          "observation_noise_variance": 6.063274815679869e-06,
          "best_valid_energy": -0.5085661952267606,
          "valid_ratio": 0.322265625,
          "feasible_hit": true,
          "approx_gap": 0.0,
          "timing": {
            "classical_overhead_seconds": 0.005706500000087544,
            "circuit_construction_seconds": 0.0,
            "transpilation_seconds": 0.0,
            "execution_seconds": 0.004466375001356937,
            "mitigation_seconds": 0.0001911670042318292,
            "queue_latency_seconds": 2.0,
            "total_seconds": 2.0103640840025037
          },
          "backend_stats": {
            "backend_name": "fast_simulator",
            "initial_state_strategy": "dicke",
            "simulator_seed": null,
            "zne_simulator_seeds": [],
            "transpiled_depth": 0,
            "transpiled_size": 0,
            "two_qubit_gate_count": 0,
            "swap_gate_count": 0,
            "shot_multiplier": 1.25,
            "effective_shots": 2560.0,
            "transpile_topology": "analytical_statevector",
            "basis_gates": [],
            "routing_method": "sabre",
            "seed_transpiler": 42,
            "execution_billing_mode": "job",
            "calibration_aware_routing": true,
            "mean_mock_cnot_error": 0.0,
            "max_mock_cnot_error": 0.0,
            "estimated_swap_risk_penalty": 0.0,
            "estimated_billed_seconds": 2.004657584002416,
            "estimated_qpu_cost_usd": 0.0
          }
        },
        {
          "evaluation_index": 5,
          "params": [
            2.008201510354696,
            2.590576005568573,
            1.120138891261518,
            2.034848554239504
          ],
          "objective": -0.40289899326150835,
          "raw_objective": -0.40289899326150835,
          "variance": 0.0010236560793829008,
          "observation_noise_variance": 4.99832070011182e-06,
          "best_valid_energy": -0.5085661952267606,
          "valid_ratio": 0.322265625,
          "feasible_hit": true,
          "approx_gap": 0.0,
          "timing": {
            "classical_overhead_seconds": 0.005725040995457675,
            "circuit_construction_seconds": 0.0,
            "transpilation_seconds": 0.0,
            "execution_seconds": 0.004499666996707674,
            "mitigation_seconds": 0.0001915419998113066,
            "queue_latency_seconds": 2.0,
            "total_seconds": 2.010416332996101
          },
          "backend_stats": {
            "backend_name": "fast_simulator",
            "initial_state_strategy": "dicke",
            "simulator_seed": null,
            "zne_simulator_seeds": [],
            "transpiled_depth": 0,
            "transpiled_size": 0,
            "two_qubit_gate_count": 0,
            "swap_gate_count": 0,
            "shot_multiplier": 1.25,
            "effective_shots": 2560.0,
            "transpile_topology": "analytical_statevector",
            "basis_gates": [],
            "routing_method": "sabre",
            "seed_transpiler": 42,
            "execution_billing_mode": "job",
            "calibration_aware_routing": true,
            "mean_mock_cnot_error": 0.0,
            "max_mock_cnot_error": 0.0,
            "estimated_swap_risk_penalty": 0.0,
            "estimated_billed_seconds": 2.0046912920006434,
            "estimated_qpu_cost_usd": 0.0
          }
        },
        {
          "evaluation_index": 6,
          "params": [
            2.2623565497225897,
            0.9815588550085804,
            2.455543751304521,
            2.5188204104436336
          ],
          "objective": -0.4204972306232521,
          "raw_objective": -0.4204972306232521,
          "variance": 0.0012658906438313966,
          "observation_noise_variance": 6.181106659332991e-06,
          "best_valid_energy": -0.5085661952267606,
          "valid_ratio": 0.31201171875,
          "feasible_hit": true,
          "approx_gap": 0.0,
          "timing": {
            "classical_overhead_seconds": 0.005732416997489054,
            "circuit_construction_seconds": 0.0,
            "transpilation_seconds": 0.0,
            "execution_seconds": 0.004499124996073078,
            "mitigation_seconds": 0.0001915419998113066,
            "queue_latency_seconds": 2.0,
            "total_seconds": 2.0104231249933946
          },
          "backend_stats": {
            "backend_name": "fast_simulator",
            "initial_state_strategy": "dicke",
            "simulator_seed": null,
            "zne_simulator_seeds": [],
            "transpiled_depth": 0,
            "transpiled_size": 0,
            "two_qubit_gate_count": 0,
            "swap_gate_count": 0,
            "shot_multiplier": 1.25,
            "effective_shots": 2560.0,
            "transpile_topology": "analytical_statevector",
            "basis_gates": [],
            "routing_method": "sabre",
            "seed_transpiler": 42,
            "execution_billing_mode": "job",
            "calibration_aware_routing": true,
            "mean_mock_cnot_error": 0.0,
            "max_mock_cnot_error": 0.0,
            "estimated_swap_risk_penalty": 0.0,
            "estimated_billed_seconds": 2.0046907079959055,
            "estimated_qpu_cost_usd": 0.0
          }
        },
        {
          "evaluation_index": 7,
          "params": [
            5.969680332368723,
            1.6814476082788343,
            2.573626922092235,
            0.03280270878341813
          ],
          "objective": -0.3712743722281452,
          "raw_objective": -0.3712743722281452,
          "variance": 0.0014495341377636084,
          "observation_noise_variance": 7.077803407048869e-06,
          "best_valid_energy": -0.5085661952267606,
          "valid_ratio": 0.34228515625,
          "feasible_hit": true,
          "approx_gap": 0.0,
          "timing": {
            "classical_overhead_seconds": 0.0056906250028987415,
            "circuit_construction_seconds": 0.0,
            "transpilation_seconds": 0.0,
            "execution_seconds": 0.0044611670018639416,
            "mitigation_seconds": 0.00019112500012852252,
            "queue_latency_seconds": 2.0,
            "total_seconds": 2.0103429580049124
          },
          "backend_stats": {
            "backend_name": "fast_simulator",
            "initial_state_strategy": "dicke",
            "simulator_seed": null,
            "zne_simulator_seeds": [],
            "transpiled_depth": 0,
            "transpiled_size": 0,
            "two_qubit_gate_count": 0,
            "swap_gate_count": 0,
            "shot_multiplier": 1.25,
            "effective_shots": 2560.0,
            "transpile_topology": "analytical_statevector",
            "basis_gates": [],
            "routing_method": "sabre",
            "seed_transpiler": 42,
            "execution_billing_mode": "job",
            "calibration_aware_routing": true,
            "mean_mock_cnot_error": 0.0,
            "max_mock_cnot_error": 0.0,
            "estimated_swap_risk_penalty": 0.0,
            "estimated_billed_seconds": 2.0046523330020136,
            "estimated_qpu_cost_usd": 0.0
          }
        },
        {
          "evaluation_index": 8,
          "params": [
            3.9526936264298214,
            0.8557556524754849,
            1.4362947206385412,
            1.751112887172665
          ],
          "objective": -0.40943955084828637,
          "raw_objective": -0.40943955084828637,
          "variance": 0.0008195757605903298,
          "observation_noise_variance": 4.00183476850747e-06,
          "best_valid_energy": -0.5085661952267606,
          "valid_ratio": 0.32666015625,
          "feasible_hit": true,
          "approx_gap": 0.0,
          "timing": {
            "classical_overhead_seconds": 0.005718291999073699,
            "circuit_construction_seconds": 0.0,
            "transpilation_seconds": 0.0,
            "execution_seconds": 0.004494666995014995,
            "mitigation_seconds": 0.0001910840001073666,
            "queue_latency_seconds": 2.0,
            "total_seconds": 2.010404083994217
          },
          "backend_stats": {
            "backend_name": "fast_simulator",
            "initial_state_strategy": "dicke",
            "simulator_seed": null,
            "zne_simulator_seeds": [],
            "transpiled_depth": 0,
            "transpiled_size": 0,
            "two_qubit_gate_count": 0,
            "swap_gate_count": 0,
            "shot_multiplier": 1.25,
            "effective_shots": 2560.0,
            "transpile_topology": "analytical_statevector",
            "basis_gates": [],
            "routing_method": "sabre",
            "seed_transpiler": 42,
            "execution_billing_mode": "job",
            "calibration_aware_routing": true,
            "mean_mock_cnot_error": 0.0,
            "max_mock_cnot_error": 0.0,
            "estimated_swap_risk_penalty": 0.0,
            "estimated_billed_seconds": 2.0046857919951435,
            "estimated_qpu_cost_usd": 0.0
          }
        },
        {
          "evaluation_index": 9,
          "params": [
            2.262969721575458,
            1.0287215605594795,
            3.1905164142294353,
            0.40139307388546797
          ],
          "objective": -0.39799650818765225,
          "raw_objective": -0.39799650818765225,
          "variance": 0.0013458390150732913,
          "observation_noise_variance": 6.571479565787555e-06,
          "best_valid_energy": -0.5085661952267606,
          "valid_ratio": 0.3203125,
          "feasible_hit": true,
          "approx_gap": 0.0,
          "timing": {
            "classical_overhead_seconds": 0.005707124997570645,
            "circuit_construction_seconds": 0.0,
            "transpilation_seconds": 0.0,
            "execution_seconds": 0.0044962920001125894,
            "mitigation_seconds": 0.00018950000230688602,
            "queue_latency_seconds": 2.0,
            "total_seconds": 2.0103929589968175
          },
          "backend_stats": {
            "backend_name": "fast_simulator",
            "initial_state_strategy": "dicke",
            "simulator_seed": null,
            "zne_simulator_seeds": [],
            "transpiled_depth": 0,
            "transpiled_size": 0,
            "two_qubit_gate_count": 0,
            "swap_gate_count": 0,
            "shot_multiplier": 1.25,
            "effective_shots": 2560.0,
            "transpile_topology": "analytical_statevector",
            "basis_gates": [],
            "routing_method": "sabre",
            "seed_transpiler": 42,
            "execution_billing_mode": "job",
            "calibration_aware_routing": true,
            "mean_mock_cnot_error": 0.0,
            "max_mock_cnot_error": 0.0,
            "estimated_swap_risk_penalty": 0.0,
            "estimated_billed_seconds": 2.004685833999247,
            "estimated_qpu_cost_usd": 0.0
          }
        },
        {
          "evaluation_index": 10,
          "params": [
            4.876510692449625,
            1.874820880165487,
            3.776010637448069,
            0.6370805442434275
          ],
          "objective": -0.40238270307327556,
          "raw_objective": -0.40238270307327556,
          "variance": 0.001168448306909653,
          "observation_noise_variance": 5.70531399858229e-06,
          "best_valid_energy": -0.5085661952267606,
          "valid_ratio": 0.32373046875,
          "feasible_hit": true,
          "approx_gap": 0.0,
          "timing": {
            "classical_overhead_seconds": 0.005740458000218496,
            "circuit_construction_seconds": 0.0,
            "transpilation_seconds": 0.0,
            "execution_seconds": 0.004519750000326894,
            "mitigation_seconds": 0.0001870419946499169,
            "queue_latency_seconds": 2.0,
            "total_seconds": 2.0104473329993198
          },
          "backend_stats": {
            "backend_name": "fast_simulator",
            "initial_state_strategy": "dicke",
            "simulator_seed": null,
            "zne_simulator_seeds": [],
            "transpiled_depth": 0,
            "transpiled_size": 0,
            "two_qubit_gate_count": 0,
            "swap_gate_count": 0,
            "shot_multiplier": 1.25,
            "effective_shots": 2560.0,
            "transpile_topology": "analytical_statevector",
            "basis_gates": [],
            "routing_method": "sabre",
            "seed_transpiler": 42,
            "execution_billing_mode": "job",
            "calibration_aware_routing": true,
            "mean_mock_cnot_error": 0.0,
            "max_mock_cnot_error": 0.0,
            "estimated_swap_risk_penalty": 0.0,
            "estimated_billed_seconds": 2.0047068749991013,
            "estimated_qpu_cost_usd": 0.0
          }
        },
        {
          "evaluation_index": 11,
          "params": [
            3.5979241923079606,
            0.6466814913898228,
            3.6076484533832582,
            2.756930624692214
          ],
          "objective": -0.3860204335332955,
          "raw_objective": -0.3860204335332955,
          "variance": 0.001869763846459177,
          "observation_noise_variance": 9.12970628153895e-06,
          "best_valid_energy": -0.5085661952267606,
          "valid_ratio": 0.31689453125,
          "feasible_hit": true,
          "approx_gap": 0.0,
          "timing": {
            "classical_overhead_seconds": 0.005709958000807092,
            "circuit_construction_seconds": 0.0,
            "transpilation_seconds": 0.0,
            "execution_seconds": 0.004501041003095452,
            "mitigation_seconds": 0.0001867500031949021,
            "queue_latency_seconds": 2.0,
            "total_seconds": 2.010397791003925
          },
          "backend_stats": {
            "backend_name": "fast_simulator",
            "initial_state_strategy": "dicke",
            "simulator_seed": null,
            "zne_simulator_seeds": [],
            "transpiled_depth": 0,
            "transpiled_size": 0,
            "two_qubit_gate_count": 0,
            "swap_gate_count": 0,
            "shot_multiplier": 1.25,
            "effective_shots": 2560.0,
            "transpile_topology": "analytical_statevector",
            "basis_gates": [],
            "routing_method": "sabre",
            "seed_transpiler": 42,
            "execution_billing_mode": "job",
            "calibration_aware_routing": true,
            "mean_mock_cnot_error": 0.0,
            "max_mock_cnot_error": 0.0,
            "estimated_swap_risk_penalty": 0.0,
            "estimated_billed_seconds": 2.0046878330031177,
            "estimated_qpu_cost_usd": 0.0
          }
        },
        {
          "evaluation_index": 12,
          "params": [
            2.73556630807518,
            0.4585133532662724,
            2.4769809273620926,
            2.2169597383571564
          ],
          "objective": -0.40178855812283293,
          "raw_objective": -0.40178855812283293,
          "variance": 0.0010529067096818057,
          "observation_noise_variance": 5.141146043368192e-06,
          "best_valid_energy": -0.5085661952267606,
          "valid_ratio": 0.318359375,
          "feasible_hit": true,
          "approx_gap": 0.0,
          "timing": {
            "classical_overhead_seconds": 0.005721416004234925,
            "circuit_construction_seconds": 0.0,
            "transpilation_seconds": 0.0,
            "execution_seconds": 0.004503124997427221,
            "mitigation_seconds": 0.0001919170026667416,
            "queue_latency_seconds": 2.0,
            "total_seconds": 2.01041649900435
          },
          "backend_stats": {
            "backend_name": "fast_simulator",
            "initial_state_strategy": "dicke",
            "simulator_seed": null,
            "zne_simulator_seeds": [],
            "transpiled_depth": 0,
            "transpiled_size": 0,
            "two_qubit_gate_count": 0,
            "swap_gate_count": 0,
            "shot_multiplier": 1.25,
            "effective_shots": 2560.0,
            "transpile_topology": "analytical_statevector",
            "basis_gates": [],
            "routing_method": "sabre",
            "seed_transpiler": 42,
            "execution_billing_mode": "job",
            "calibration_aware_routing": true,
            "mean_mock_cnot_error": 0.0,
            "max_mock_cnot_error": 0.0,
            "estimated_swap_risk_penalty": 0.0,
            "estimated_billed_seconds": 2.004695083000115,
            "estimated_qpu_cost_usd": 0.0
          }
        }
      ]
    },
    "spsa": {
      "method": "spsa",
      "best_objective": -0.41124031790273613,
      "best_raw_objective": -0.41124031790273613,
      "best_valid_energy": -0.5085661952267606,
      "best_valid_ratio": 0.34912109375,
      "feasible_hit_rate": 1.0,
      "mean_objective_variance": 0.0010193158885692642,
      "mean_approx_gap": 0.0,
      "objective_history": [
        -0.40268345813870926,
        -0.40268345813870926,
        -0.4106741472286711,
        -0.4106741472286711,
        -0.4106741472286711,
        -0.4106741472286711,
        -0.41124031790273613,
        -0.41124031790273613,
        -0.41124031790273613,
        -0.41124031790273613,
        -0.41124031790273613,
        -0.41124031790273613
      ],
      "raw_objective_history": [
        -0.40268345813870926,
        -0.40268345813870926,
        -0.4106741472286711,
        -0.4106741472286711,
        -0.4106741472286711,
        -0.4106741472286711,
        -0.41124031790273613,
        -0.41124031790273613,
        -0.41124031790273613,
        -0.41124031790273613,
        -0.41124031790273613,
        -0.41124031790273613
      ],
      "best_valid_history": [
        -0.5085661952267606,
        -0.5085661952267606,
        -0.5085661952267606,
        -0.5085661952267606,
        -0.5085661952267606,
        -0.5085661952267606,
        -0.5085661952267606,
        -0.5085661952267606,
        -0.5085661952267606,
        -0.5085661952267606,
        -0.5085661952267606,
        -0.5085661952267606
      ],
      "valid_ratio_history": [
        0.31298828125,
        0.322265625,
        0.32470703125,
        0.31591796875,
        0.33056640625,
        0.32177734375,
        0.34912109375,
        0.326171875,
        0.3095703125,
        0.31201171875,
        0.32666015625,
        0.333984375
      ],
      "feasible_hit_history": [
        1.0,
        1.0,
        1.0,
        1.0,
        1.0,
        1.0,
        1.0,
        1.0,
        1.0,
        1.0,
        1.0,
        1.0
      ],
      "variance_history": [
        0.0008065856001847338,
        0.0012149999166407022,
        0.0009653444476438455,
        0.0011852428183314057,
        0.0010452954394946368,
        0.0010800686819784355,
        0.0009477141397541411,
        0.0009089280273061884,
        0.000816930735232424,
        0.0013655974637289126,
        0.0010764735586994978,
        0.000818609833836248
      ],
      "approx_gap_history": [
        0.0,
        0.0,
        0.0,
        0.0,
        0.0,
        0.0,
        0.0,
        0.0,
        0.0,
        0.0,
        0.0,
        0.0
      ],
      "elapsed_seconds": 0.0709132080010022,
      "total_objective_calls": 12,
      "timing_totals": {
        "classical_overhead_seconds": 0.00019316501857247204,
        "circuit_construction_seconds": 0.0,
        "transpilation_seconds": 0.0,
        "execution_seconds": 0.05501100199035136,
        "mitigation_seconds": 0.002745333971688524,
        "queue_latency_seconds": 24.0,
        "total_seconds": 24.057950125003117
      },
      "total_effective_shots": 30720.0,
      "total_estimated_billed_seconds": 24.057756959984545,
      "total_estimated_qpu_cost_usd": 0.0,
      "best_params": [
        5.894471233505723,
        0.9477803853830804,
        5.572456421475636,
        2.008896929028301
      ],
      "evaluation_records": [
        {
          "evaluation_index": 1,
          "params": [
            5.908261440558109,
            0.948201770698219,
            5.572877806790774,
            2.1831872263614436
          ],
          "objective": -0.40268345813870926,
          "raw_objective": -0.40268345813870926,
          "variance": 0.0008065856001847338,
          "observation_noise_variance": 3.9384062509020205e-06,
          "best_valid_energy": -0.5085661952267606,
          "valid_ratio": 0.31298828125,
          "feasible_hit": true,
          "approx_gap": 0.0,
          "timing": {
            "classical_overhead_seconds": 2.1708001440856606e-05,
            "circuit_construction_seconds": 0.0,
            "transpilation_seconds": 0.0,
            "execution_seconds": 0.004499624999880325,
            "mitigation_seconds": 0.00019091699505224824,
            "queue_latency_seconds": 2.0,
            "total_seconds": 2.0047122909963946
          },
          "backend_stats": {
            "backend_name": "fast_simulator",
            "initial_state_strategy": "dicke",
            "simulator_seed": null,
            "zne_simulator_seeds": [],
            "transpiled_depth": 0,
            "transpiled_size": 0,
            "two_qubit_gate_count": 0,
            "swap_gate_count": 0,
            "shot_multiplier": 1.25,
            "effective_shots": 2560.0,
            "transpile_topology": "analytical_statevector",
            "basis_gates": [],
            "routing_method": "sabre",
            "seed_transpiler": 42,
            "execution_billing_mode": "job",
            "calibration_aware_routing": true,
            "mean_mock_cnot_error": 0.0,
            "max_mock_cnot_error": 0.0,
            "estimated_swap_risk_penalty": 0.0,
            "estimated_billed_seconds": 2.0046905829949537,
            "estimated_qpu_cost_usd": 0.0
          }
        },
        {
          "evaluation_index": 2,
          "params": [
            5.708261440558109,
            0.748201770698219,
            5.3728778067907745,
            1.9831872263614434
          ],
          "objective": -0.39073704233218515,
          "raw_objective": -0.39073704233218515,
          "variance": 0.0012149999166407022,
          "observation_noise_variance": 5.9326167804721786e-06,
          "best_valid_energy": -0.5085661952267606,
          "valid_ratio": 0.322265625,
          "feasible_hit": true,
          "approx_gap": 0.0,
          "timing": {
            "classical_overhead_seconds": 4.41699376096949e-06,
            "circuit_construction_seconds": 0.0,
            "transpilation_seconds": 0.0,
            "execution_seconds": 0.004506167002546135,
            "mitigation_seconds": 0.00018679200002225116,
            "queue_latency_seconds": 2.0,
            "total_seconds": 2.0046974169963505
          },
          "backend_stats": {
            "backend_name": "fast_simulator",
            "initial_state_strategy": "dicke",
            "simulator_seed": null,
            "zne_simulator_seeds": [],
            "transpiled_depth": 0,
            "transpiled_size": 0,
            "two_qubit_gate_count": 0,
            "swap_gate_count": 0,
            "shot_multiplier": 1.25,
            "effective_shots": 2560.0,
            "transpile_topology": "analytical_statevector",
            "basis_gates": [],
            "routing_method": "sabre",
            "seed_transpiler": 42,
            "execution_billing_mode": "job",
            "calibration_aware_routing": true,
            "mean_mock_cnot_error": 0.0,
            "max_mock_cnot_error": 0.0,
            "estimated_swap_risk_penalty": 0.0,
            "estimated_billed_seconds": 2.0046930000025895,
            "estimated_qpu_cost_usd": 0.0
          }
        },
        {
          "evaluation_index": 3,
          "params": [
            5.719085265722554,
            0.9455028931500302,
            5.570178929242585,
            2.1804883488132547
          ],
          "objective": -0.4106741472286711,
          "raw_objective": -0.4106741472286711,
          "variance": 0.0009653444476438455,
          "observation_noise_variance": 4.7135959357609645e-06,
          "best_valid_energy": -0.5085661952267606,
          "valid_ratio": 0.32470703125,
          "feasible_hit": true,
          "approx_gap": 0.0,
          "timing": {
            "classical_overhead_seconds": 1.554200571263209e-05,
            "circuit_construction_seconds": 0.0,
            "transpilation_seconds": 0.0,
            "execution_seconds": 0.004488124999625143,
            "mitigation_seconds": 0.00018812499911291525,
            "queue_latency_seconds": 2.0,
            "total_seconds": 2.004691834008554
          },
          "backend_stats": {
            "backend_name": "fast_simulator",
            "initial_state_strategy": "dicke",
            "simulator_seed": null,
            "zne_simulator_seeds": [],
            "transpiled_depth": 0,
            "transpiled_size": 0,
            "two_qubit_gate_count": 0,
            "swap_gate_count": 0,
            "shot_multiplier": 1.25,
            "effective_shots": 2560.0,
            "transpile_topology": "analytical_statevector",
            "basis_gates": [],
            "routing_method": "sabre",
            "seed_transpiler": 42,
            "execution_billing_mode": "job",
            "calibration_aware_routing": true,
            "mean_mock_cnot_error": 0.0,
            "max_mock_cnot_error": 0.0,
            "estimated_swap_risk_penalty": 0.0,
            "estimated_billed_seconds": 2.0046762920028414,
            "estimated_qpu_cost_usd": 0.0
          }
        },
        {
          "evaluation_index": 4,
          "params": [
            5.90556256300992,
            0.7590255958626637,
            5.383701631955219,
            1.9940110515258884
          ],
          "objective": -0.39056432982615186,
          "raw_objective": -0.39056432982615186,
          "variance": 0.0011852428183314057,
          "observation_noise_variance": 5.787318448883817e-06,
          "best_valid_energy": -0.5085661952267606,
          "valid_ratio": 0.31591796875,
          "feasible_hit": true,
          "approx_gap": 0.0,
          "timing": {
            "classical_overhead_seconds": 4.29100327892229e-06,
            "circuit_construction_seconds": 0.0,
            "transpilation_seconds": 0.0,
            "execution_seconds": 0.004514916996413376,
            "mitigation_seconds": 0.00018995899881701916,
            "queue_latency_seconds": 2.0,
            "total_seconds": 2.0047092079985305
          },
          "backend_stats": {
            "backend_name": "fast_simulator",
            "initial_state_strategy": "dicke",
            "simulator_seed": null,
            "zne_simulator_seeds": [],
            "transpiled_depth": 0,
            "transpiled_size": 0,
            "two_qubit_gate_count": 0,
            "swap_gate_count": 0,
            "shot_multiplier": 1.25,
            "effective_shots": 2560.0,
            "transpile_topology": "analytical_statevector",
            "basis_gates": [],
            "routing_method": "sabre",
            "seed_transpiler": 42,
            "execution_billing_mode": "job",
            "calibration_aware_routing": true,
            "mean_mock_cnot_error": 0.0,
            "max_mock_cnot_error": 0.0,
            "estimated_swap_risk_penalty": 0.0,
            "estimated_billed_seconds": 2.0047049169952516,
            "estimated_qpu_cost_usd": 0.0
          }
        },
        {
          "evaluation_index": 5,
          "params": [
            5.89513697243329,
            0.9484461243106467,
            5.573122160403202,
            2.1834315799738713
          ],
          "objective": -0.4021145460641358,
          "raw_objective": -0.4021145460641358,
          "variance": 0.0010452954394946368,
          "observation_noise_variance": 5.103981638157406e-06,
          "best_valid_energy": -0.5085661952267606,
          "valid_ratio": 0.33056640625,
          "feasible_hit": true,
          "approx_gap": 0.0,
          "timing": {
            "classical_overhead_seconds": 1.479100319556892e-05,
            "circuit_construction_seconds": 0.0,
            "transpilation_seconds": 0.0,
            "execution_seconds": 0.004502042000240181,
            "mitigation_seconds": 0.00018333299522055313,
            "queue_latency_seconds": 2.0,
            "total_seconds": 2.0047002080027596
          },
          "backend_stats": {
            "backend_name": "fast_simulator",
            "initial_state_strategy": "dicke",
            "simulator_seed": null,
            "zne_simulator_seeds": [],
            "transpiled_depth": 0,
            "transpiled_size": 0,
            "two_qubit_gate_count": 0,
            "swap_gate_count": 0,
            "shot_multiplier": 1.25,
            "effective_shots": 2560.0,
            "transpile_topology": "analytical_statevector",
            "basis_gates": [],
            "routing_method": "sabre",
            "seed_transpiler": 42,
            "execution_billing_mode": "job",
            "calibration_aware_routing": true,
            "mean_mock_cnot_error": 0.0,
            "max_mock_cnot_error": 0.0,
            "estimated_swap_risk_penalty": 0.0,
            "estimated_billed_seconds": 2.004685416999564,
            "estimated_qpu_cost_usd": 0.0
          }
        },
        {
          "evaluation_index": 6,
          "params": [
            5.716142034561937,
            0.769451186439294,
            5.394127222531849,
            2.004436642102519
          ],
          "objective": -0.3961770821865013,
          "raw_objective": -0.3961770821865013,
          "variance": 0.0010800686819784355,
          "observation_noise_variance": 5.27377286122283e-06,
          "best_valid_energy": -0.5085661952267606,
          "valid_ratio": 0.32177734375,
          "feasible_hit": true,
          "approx_gap": 0.0,
          "timing": {
            "classical_overhead_seconds": 4.29100327892229e-06,
            "circuit_construction_seconds": 0.0,
            "transpilation_seconds": 0.0,
            "execution_seconds": 0.004499957998632453,
            "mitigation_seconds": 0.00018941600137623027,
            "queue_latency_seconds": 2.0,
            "total_seconds": 2.004693707007391
          },
          "backend_stats": {
            "backend_name": "fast_simulator",
            "initial_state_strategy": "dicke",
            "simulator_seed": null,
            "zne_simulator_seeds": [],
            "transpiled_depth": 0,
            "transpiled_size": 0,
            "two_qubit_gate_count": 0,
            "swap_gate_count": 0,
            "shot_multiplier": 1.25,
            "effective_shots": 2560.0,
            "transpile_topology": "analytical_statevector",
            "basis_gates": [],
            "routing_method": "sabre",
            "seed_transpiler": 42,
            "execution_billing_mode": "job",
            "calibration_aware_routing": true,
            "mean_mock_cnot_error": 0.0,
            "max_mock_cnot_error": 0.0,
            "estimated_swap_risk_penalty": 0.0,
            "estimated_billed_seconds": 2.004689416004112,
            "estimated_qpu_cost_usd": 0.0
          }
        },
        {
          "evaluation_index": 7,
          "params": [
            5.894471233505723,
            0.9477803853830804,
            5.572456421475636,
            2.008896929028301
          ],
          "objective": -0.41124031790273613,
          "raw_objective": -0.41124031790273613,
          "variance": 0.0009477141397541411,
          "observation_noise_variance": 4.627510448018267e-06,
          "best_valid_energy": -0.5085661952267606,
          "valid_ratio": 0.34912109375,
          "feasible_hit": true,
          "approx_gap": 0.0,
          "timing": {
            "classical_overhead_seconds": 1.4416000340133905e-05,
            "circuit_construction_seconds": 0.0,
            "transpilation_seconds": 0.0,
            "execution_seconds": 0.004754417001095135,
            "mitigation_seconds": 0.00032241699955193326,
            "queue_latency_seconds": 2.0,
            "total_seconds": 2.0050913329978357
          },
          "backend_stats": {
            "backend_name": "fast_simulator",
            "initial_state_strategy": "dicke",
            "simulator_seed": null,
            "zne_simulator_seeds": [],
            "transpiled_depth": 0,
            "transpiled_size": 0,
            "two_qubit_gate_count": 0,
            "swap_gate_count": 0,
            "shot_multiplier": 1.25,
            "effective_shots": 2560.0,
            "transpile_topology": "analytical_statevector",
            "basis_gates": [],
            "routing_method": "sabre",
            "seed_transpiler": 42,
            "execution_billing_mode": "job",
            "calibration_aware_routing": true,
            "mean_mock_cnot_error": 0.0,
            "max_mock_cnot_error": 0.0,
            "estimated_swap_risk_penalty": 0.0,
            "estimated_billed_seconds": 2.0050769169974956,
            "estimated_qpu_cost_usd": 0.0
          }
        },
        {
          "evaluation_index": 8,
          "params": [
            5.720602321487719,
            0.773911473365076,
            5.398587509457631,
            2.182765841046305
          ],
          "objective": -0.3876180022084294,
          "raw_objective": -0.3876180022084294,
          "variance": 0.0009089280273061884,
          "observation_noise_variance": 4.438125133330998e-06,
          "best_valid_energy": -0.5085661952267606,
          "valid_ratio": 0.326171875,
          "feasible_hit": true,
          "approx_gap": 0.0,
          "timing": {
            "classical_overhead_seconds": 7.624999852851033e-06,
            "circuit_construction_seconds": 0.0,
            "transpilation_seconds": 0.0,
            "execution_seconds": 0.0046750420005992055,
            "mitigation_seconds": 0.00024458299594698474,
            "queue_latency_seconds": 2.0,
            "total_seconds": 2.0049272920005023
          },
          "backend_stats": {
            "backend_name": "fast_simulator",
            "initial_state_strategy": "dicke",
            "simulator_seed": null,
            "zne_simulator_seeds": [],
            "transpiled_depth": 0,
            "transpiled_size": 0,
            "two_qubit_gate_count": 0,
            "swap_gate_count": 0,
            "shot_multiplier": 1.25,
            "effective_shots": 2560.0,
            "transpile_topology": "analytical_statevector",
            "basis_gates": [],
            "routing_method": "sabre",
            "seed_transpiler": 42,
            "execution_billing_mode": "job",
            "calibration_aware_routing": true,
            "mean_mock_cnot_error": 0.0,
            "max_mock_cnot_error": 0.0,
            "estimated_swap_risk_penalty": 0.0,
            "estimated_billed_seconds": 2.0049196670006495,
            "estimated_qpu_cost_usd": 0.0
          }
        },
        {
          "evaluation_index": 9,
          "params": [
            5.899772828089665,
            0.953081979967022,
            5.577758016059577,
            2.1735895036024857
          ],
          "objective": -0.3976836642271393,
          "raw_objective": -0.3976836642271393,
          "variance": 0.000816930735232424,
          "observation_noise_variance": 3.98891960562707e-06,
          "best_valid_energy": -0.5085661952267606,
          "valid_ratio": 0.3095703125,
          "feasible_hit": true,
          "approx_gap": 0.0,
          "timing": {
            "classical_overhead_seconds": 3.074999403906986e-05,
            "circuit_construction_seconds": 0.0,
            "transpilation_seconds": 0.0,
            "execution_seconds": 0.0046485830025631,
            "mitigation_seconds": 0.0002815409970935434,
            "queue_latency_seconds": 2.0,
            "total_seconds": 2.0049609579946264
          },
          "backend_stats": {
            "backend_name": "fast_simulator",
            "initial_state_strategy": "dicke",
            "simulator_seed": null,
            "zne_simulator_seeds": [],
            "transpiled_depth": 0,
            "transpiled_size": 0,
            "two_qubit_gate_count": 0,
            "swap_gate_count": 0,
            "shot_multiplier": 1.25,
            "effective_shots": 2560.0,
            "transpile_topology": "analytical_statevector",
            "basis_gates": [],
            "routing_method": "sabre",
            "seed_transpiler": 42,
            "execution_billing_mode": "job",
            "calibration_aware_routing": true,
            "mean_mock_cnot_error": 0.0,
            "max_mock_cnot_error": 0.0,
            "estimated_swap_risk_penalty": 0.0,
            "estimated_billed_seconds": 2.0049302080005873,
            "estimated_qpu_cost_usd": 0.0
          }
        },
        {
          "evaluation_index": 10,
          "params": [
            5.729778658931538,
            0.7830878108088952,
            5.40776384690145,
            2.003595334444359
          ],
          "objective": -0.383892104580163,
          "raw_objective": -0.383892104580163,
          "variance": 0.0013655974637289126,
          "observation_noise_variance": 6.667956365863831e-06,
          "best_valid_energy": -0.5085661952267606,
          "valid_ratio": 0.31201171875,
          "feasible_hit": true,
          "approx_gap": 0.0,
          "timing": {
            "classical_overhead_seconds": 1.0209005267824978e-05,
            "circuit_construction_seconds": 0.0,
            "transpilation_seconds": 0.0,
            "execution_seconds": 0.0046779169933870435,
            "mitigation_seconds": 0.0002889589959522709,
            "queue_latency_seconds": 2.0,
            "total_seconds": 2.0049771679987316
          },
          "backend_stats": {
            "backend_name": "fast_simulator",
            "initial_state_strategy": "dicke",
            "simulator_seed": null,
            "zne_simulator_seeds": [],
            "transpiled_depth": 0,
            "transpiled_size": 0,
            "two_qubit_gate_count": 0,
            "swap_gate_count": 0,
            "shot_multiplier": 1.25,
            "effective_shots": 2560.0,
            "transpile_topology": "analytical_statevector",
            "basis_gates": [],
            "routing_method": "sabre",
            "seed_transpiler": 42,
            "execution_billing_mode": "job",
            "calibration_aware_routing": true,
            "mean_mock_cnot_error": 0.0,
            "max_mock_cnot_error": 0.0,
            "estimated_swap_risk_penalty": 0.0,
            "estimated_billed_seconds": 2.0049669589934638,
            "estimated_qpu_cost_usd": 0.0
          }
        },
        {
          "evaluation_index": 11,
          "params": [
            5.902279014703819,
            0.9555881665811756,
            5.580264202673731,
            2.1760956902166395
          ],
          "objective": -0.40254366426549976,
          "raw_objective": -0.40254366426549976,
          "variance": 0.0010764735586994978,
          "observation_noise_variance": 5.2562185483373916e-06,
          "best_valid_energy": -0.5085661952267606,
          "valid_ratio": 0.32666015625,
          "feasible_hit": true,
          "approx_gap": 0.0,
          "timing": {
            "classical_overhead_seconds": 2.983299782499671e-05,
            "circuit_construction_seconds": 0.0,
            "transpilation_seconds": 0.0,
            "execution_seconds": 0.00464833399746567,
            "mitigation_seconds": 0.0002459169991197996,
            "queue_latency_seconds": 2.0,
            "total_seconds": 2.0049241249944316
          },
          "backend_stats": {
            "backend_name": "fast_simulator",
            "initial_state_strategy": "dicke",
            "simulator_seed": null,
            "zne_simulator_seeds": [],
            "transpiled_depth": 0,
            "transpiled_size": 0,
            "two_qubit_gate_count": 0,
            "swap_gate_count": 0,
            "shot_multiplier": 1.25,
            "effective_shots": 2560.0,
            "transpile_topology": "analytical_statevector",
            "basis_gates": [],
            "routing_method": "sabre",
            "seed_transpiler": 42,
            "execution_billing_mode": "job",
            "calibration_aware_routing": true,
            "mean_mock_cnot_error": 0.0,
            "max_mock_cnot_error": 0.0,
            "estimated_swap_risk_penalty": 0.0,
            "estimated_billed_seconds": 2.0048942919966066,
            "estimated_qpu_cost_usd": 0.0
          }
        },
        {
          "evaluation_index": 12,
          "params": [
            5.735386553491969,
            0.788695705369326,
            5.413371741461881,
            2.0092032290047896
          ],
          "objective": -0.39472322160146317,
          "raw_objective": -0.39472322160146317,
          "variance": 0.000818609833836248,
          "observation_noise_variance": 3.9971183292785545e-06,
          "best_valid_energy": -0.5085661952267606,
          "valid_ratio": 0.333984375,
          "feasible_hit": true,
          "approx_gap": 0.0,
          "timing": {
            "classical_overhead_seconds": 5.49999822396785e-06,
            "circuit_construction_seconds": 0.0,
            "transpilation_seconds": 0.0,
            "execution_seconds": 0.004595874997903593,
            "mitigation_seconds": 0.00023337499442277476,
            "queue_latency_seconds": 2.0,
            "total_seconds": 2.0048347919946536
          },
          "backend_stats": {
            "backend_name": "fast_simulator",
            "initial_state_strategy": "dicke",
            "simulator_seed": null,
            "zne_simulator_seeds": [],
            "transpiled_depth": 0,
            "transpiled_size": 0,
            "two_qubit_gate_count": 0,
            "swap_gate_count": 0,
            "shot_multiplier": 1.25,
            "effective_shots": 2560.0,
            "transpile_topology": "analytical_statevector",
            "basis_gates": [],
            "routing_method": "sabre",
            "seed_transpiler": 42,
            "execution_billing_mode": "job",
            "calibration_aware_routing": true,
            "mean_mock_cnot_error": 0.0,
            "max_mock_cnot_error": 0.0,
            "estimated_swap_risk_penalty": 0.0,
            "estimated_billed_seconds": 2.0048292919964297,
            "estimated_qpu_cost_usd": 0.0
          }
        }
      ]
    },
    "bayesian_optimization": {
      "method": "bayesian_optimization",
      "best_objective": -0.4426192398847948,
      "best_raw_objective": -0.4426192398847948,
      "best_valid_energy": -0.5085661952267606,
      "best_valid_ratio": 0.3505859375,
      "feasible_hit_rate": 1.0,
      "mean_objective_variance": 0.0011951755015686242,
      "mean_approx_gap": 0.0,
      "objective_history": [
        -0.40067041510169765,
        -0.42937967255117876,
        -0.43828023927507553,
        -0.43828023927507553,
        -0.43828023927507553,
        -0.43828023927507553,
        -0.43828023927507553,
        -0.43828023927507553,
        -0.43828023927507553,
        -0.43828023927507553,
        -0.4426192398847948,
        -0.4426192398847948
      ],
      "raw_objective_history": [
        -0.40067041510169765,
        -0.42937967255117876,
        -0.43828023927507553,
        -0.43828023927507553,
        -0.43828023927507553,
        -0.43828023927507553,
        -0.43828023927507553,
        -0.43828023927507553,
        -0.43828023927507553,
        -0.43828023927507553,
        -0.4426192398847948,
        -0.4426192398847948
      ],
      "best_valid_history": [
        -0.5085661952267606,
        -0.5085661952267606,
        -0.5085661952267606,
        -0.5085661952267606,
        -0.5085661952267606,
        -0.5085661952267606,
        -0.5085661952267606,
        -0.5085661952267606,
        -0.5085661952267606,
        -0.5085661952267606,
        -0.5085661952267606,
        -0.5085661952267606
      ],
      "valid_ratio_history": [
        0.3505859375,
        0.3251953125,
        0.337890625,
        0.33154296875,
        0.31494140625,
        0.3251953125,
        0.326171875,
        0.32080078125,
        0.31298828125,
        0.328125,
        0.3232421875,
        0.32421875
      ],
      "feasible_hit_history": [
        1.0,
        1.0,
        1.0,
        1.0,
        1.0,
        1.0,
        1.0,
        1.0,
        1.0,
        1.0,
        1.0,
        1.0
      ],
      "variance_history": [
        0.0008432458190507364,
        0.0013763520597604717,
        0.0014834835259555368,
        0.0009131862830489557,
        0.0014443593168024238,
        0.0012081065330093455,
        0.0012795872829470811,
        0.0010965083777509654,
        0.0013053911538596918,
        0.0010415400374726713,
        0.0014250724833118344,
        0.0009252731458537777
      ],
      "approx_gap_history": [
        0.0,
        0.0,
        0.0,
        0.0,
        0.0,
        0.0,
        0.0,
        0.0,
        0.0,
        0.0,
        0.0,
        0.0
      ],
      "elapsed_seconds": 0.7582693750009639,
      "total_objective_calls": 12,
      "timing_totals": {
        "classical_overhead_seconds": 0.6841176689922577,
        "circuit_construction_seconds": 0.0,
        "transpilation_seconds": 0.0,
        "execution_seconds": 0.05710591602110071,
        "mitigation_seconds": 0.003380248999746982,
        "queue_latency_seconds": 24.0,
        "total_seconds": 24.744604709005216
      },
      "total_effective_shots": 30720.0,
      "total_estimated_billed_seconds": 24.06048704001296,
      "total_estimated_qpu_cost_usd": 0.0,
      "best_params": [
        3.407360197879898,
        0.0,
        6.069788556633672,
        1.3212880523995028
      ],
      "evaluation_records": [
        {
          "evaluation_index": 1,
          "params": [
            0.9768174011427534,
            1.8496042750764798,
            3.817237237218675,
            0.7615220266433731
          ],
          "objective": -0.40067041510169765,
          "raw_objective": -0.40067041510169765,
          "variance": 0.0008432458190507364,
          "observation_noise_variance": 4.117411225833674e-06,
          "best_valid_energy": -0.5085661952267606,
          "valid_ratio": 0.3505859375,
          "feasible_hit": true,
          "approx_gap": 0.0,
          "timing": {
            "classical_overhead_seconds": 2.275099541293457e-05,
            "circuit_construction_seconds": 0.0,
            "transpilation_seconds": 0.0,
            "execution_seconds": 0.004692082999099512,
            "mitigation_seconds": 0.0002818749999278225,
            "queue_latency_seconds": 2.0,
            "total_seconds": 2.004996833995392
          },
          "backend_stats": {
            "backend_name": "fast_simulator",
            "initial_state_strategy": "dicke",
            "simulator_seed": null,
            "zne_simulator_seeds": [],
            "transpiled_depth": 0,
            "transpiled_size": 0,
            "two_qubit_gate_count": 0,
            "swap_gate_count": 0,
            "shot_multiplier": 1.25,
            "effective_shots": 2560.0,
            "transpile_topology": "analytical_statevector",
            "basis_gates": [],
            "routing_method": "sabre",
            "seed_transpiler": 42,
            "execution_billing_mode": "job",
            "calibration_aware_routing": true,
            "mean_mock_cnot_error": 0.0,
            "max_mock_cnot_error": 0.0,
            "estimated_swap_risk_penalty": 0.0,
            "estimated_billed_seconds": 2.004974082999979,
            "estimated_qpu_cost_usd": 0.0
          }
        },
        {
          "evaluation_index": 2,
          "params": [
            5.5590842656475905,
            0.47659163746326566,
            0.12169090352030172,
            1.8861323418056508
          ],
          "objective": -0.42937967255117876,
          "raw_objective": -0.42937967255117876,
          "variance": 0.0013763520597604717,
          "observation_noise_variance": 6.720469041799178e-06,
          "best_valid_energy": -0.5085661952267606,
          "valid_ratio": 0.3251953125,
          "feasible_hit": true,
          "approx_gap": 0.0,
          "timing": {
            "classical_overhead_seconds": 1.920799695653841e-05,
            "circuit_construction_seconds": 0.0,
            "transpilation_seconds": 0.0,
            "execution_seconds": 0.004756041002110578,
            "mitigation_seconds": 0.0002844580012606457,
            "queue_latency_seconds": 2.0,
            "total_seconds": 2.0050597910012584
          },
          "backend_stats": {
            "backend_name": "fast_simulator",
            "initial_state_strategy": "dicke",
            "simulator_seed": null,
            "zne_simulator_seeds": [],
            "transpiled_depth": 0,
            "transpiled_size": 0,
            "two_qubit_gate_count": 0,
            "swap_gate_count": 0,
            "shot_multiplier": 1.25,
            "effective_shots": 2560.0,
            "transpile_topology": "analytical_statevector",
            "basis_gates": [],
            "routing_method": "sabre",
            "seed_transpiler": 42,
            "execution_billing_mode": "job",
            "calibration_aware_routing": true,
            "mean_mock_cnot_error": 0.0,
            "max_mock_cnot_error": 0.0,
            "estimated_swap_risk_penalty": 0.0,
            "estimated_billed_seconds": 2.005040583004302,
            "estimated_qpu_cost_usd": 0.0
          }
        },
        {
          "evaluation_index": 3,
          "params": [
            3.458936035049703,
            2.7922639376180287,
            5.330245309677965,
            1.490737075754312
          ],
          "objective": -0.43828023927507553,
          "raw_objective": -0.43828023927507553,
          "variance": 0.0014834835259555368,
          "observation_noise_variance": 7.2435719040797695e-06,
          "best_valid_energy": -0.5085661952267606,
          "valid_ratio": 0.337890625,
          "feasible_hit": true,
          "approx_gap": 0.0,
          "timing": {
            "classical_overhead_seconds": 1.8667000404093415e-05,
            "circuit_construction_seconds": 0.0,
            "transpilation_seconds": 0.0,
            "execution_seconds": 0.004628875001799315,
            "mitigation_seconds": 0.00023624999448657036,
            "queue_latency_seconds": 2.0,
            "total_seconds": 2.00488379199669
          },
          "backend_stats": {
            "backend_name": "fast_simulator",
            "initial_state_strategy": "dicke",
            "simulator_seed": null,
            "zne_simulator_seeds": [],
            "transpiled_depth": 0,
            "transpiled_size": 0,
            "two_qubit_gate_count": 0,
            "swap_gate_count": 0,
            "shot_multiplier": 1.25,
            "effective_shots": 2560.0,
            "transpile_topology": "analytical_statevector",
            "basis_gates": [],
            "routing_method": "sabre",
            "seed_transpiler": 42,
            "execution_billing_mode": "job",
            "calibration_aware_routing": true,
            "mean_mock_cnot_error": 0.0,
            "max_mock_cnot_error": 0.0,
            "estimated_swap_risk_penalty": 0.0,
            "estimated_billed_seconds": 2.004865124996286,
            "estimated_qpu_cost_usd": 0.0
          }
        },
        {
          "evaluation_index": 4,
          "params": [
            1.8006821820520795,
            1.0296171721222909,
            1.7270747742480914,
            2.733850075143332
          ],
          "objective": -0.42029632985158116,
          "raw_objective": -0.42029632985158116,
          "variance": 0.0009131862830489557,
          "observation_noise_variance": 4.458917397699979e-06,
          "best_valid_energy": -0.5085661952267606,
          "valid_ratio": 0.33154296875,
          "feasible_hit": true,
          "approx_gap": 0.0,
          "timing": {
            "classical_overhead_seconds": 1.9999999494757503e-05,
            "circuit_construction_seconds": 0.0,
            "transpilation_seconds": 0.0,
            "execution_seconds": 0.00463270799809834,
            "mitigation_seconds": 0.0002699590040720068,
            "queue_latency_seconds": 2.0,
            "total_seconds": 2.0049227499985136
          },
          "backend_stats": {
            "backend_name": "fast_simulator",
            "initial_state_strategy": "dicke",
            "simulator_seed": null,
            "zne_simulator_seeds": [],
            "transpiled_depth": 0,
            "transpiled_size": 0,
            "two_qubit_gate_count": 0,
            "swap_gate_count": 0,
            "shot_multiplier": 1.25,
            "effective_shots": 2560.0,
            "transpile_topology": "analytical_statevector",
            "basis_gates": [],
            "routing_method": "sabre",
            "seed_transpiler": 42,
            "execution_billing_mode": "job",
            "calibration_aware_routing": true,
            "mean_mock_cnot_error": 0.0,
            "max_mock_cnot_error": 0.0,
            "estimated_swap_risk_penalty": 0.0,
            "estimated_billed_seconds": 2.004902749999019,
            "estimated_qpu_cost_usd": 0.0
          }
        },
        {
          "evaluation_index": 5,
          "params": [
            4.4227040889734175,
            3.118662811529591,
            5.945038500666617,
            1.7616202563850145
          ],
          "objective": -0.35562365805070645,
          "raw_objective": -0.35562365805070645,
          "variance": 0.0014443593168024238,
          "observation_noise_variance": 7.052535726574335e-06,
          "best_valid_energy": -0.5085661952267606,
          "valid_ratio": 0.31494140625,
          "feasible_hit": true,
          "approx_gap": 0.0,
          "timing": {
            "classical_overhead_seconds": 0.06443412500084378,
            "circuit_construction_seconds": 0.0,
            "transpilation_seconds": 0.0,
            "execution_seconds": 0.004768750004586764,
            "mitigation_seconds": 0.000276250000752043,
            "queue_latency_seconds": 2.0,
            "total_seconds": 2.0694791660062037
          },
          "backend_stats": {
            "backend_name": "fast_simulator",
            "initial_state_strategy": "dicke",
            "simulator_seed": null,
            "zne_simulator_seeds": [],
            "transpiled_depth": 0,
            "transpiled_size": 0,
            "two_qubit_gate_count": 0,
            "swap_gate_count": 0,
            "shot_multiplier": 1.25,
            "effective_shots": 2560.0,
            "transpile_topology": "analytical_statevector",
            "basis_gates": [],
            "routing_method": "sabre",
            "seed_transpiler": 42,
            "execution_billing_mode": "job",
            "calibration_aware_routing": true,
            "mean_mock_cnot_error": 0.0,
            "max_mock_cnot_error": 0.0,
            "estimated_swap_risk_penalty": 0.0,
            "estimated_billed_seconds": 2.00504504100536,
            "estimated_qpu_cost_usd": 0.0
          }
        },
        {
          "evaluation_index": 6,
          "params": [
            3.023641660606929,
            2.630914118065837,
            5.024912945943516,
            1.3886873776849893
          ],
          "objective": -0.42460281603558697,
          "raw_objective": -0.42460281603558697,
          "variance": 0.0012081065330093455,
          "observation_noise_variance": 5.898957680709695e-06,
          "best_valid_energy": -0.5085661952267606,
          "valid_ratio": 0.3251953125,
          "feasible_hit": true,
          "approx_gap": 0.0,
          "timing": {
            "classical_overhead_seconds": 0.06099975100369193,
            "circuit_construction_seconds": 0.0,
            "transpilation_seconds": 0.0,
            "execution_seconds": 0.004732541005068924,
            "mitigation_seconds": 0.00032266599737340584,
            "queue_latency_seconds": 2.0,
            "total_seconds": 2.066055042007065
          },
          "backend_stats": {
            "backend_name": "fast_simulator",
            "initial_state_strategy": "dicke",
            "simulator_seed": null,
            "zne_simulator_seeds": [],
            "transpiled_depth": 0,
            "transpiled_size": 0,
            "two_qubit_gate_count": 0,
            "swap_gate_count": 0,
            "shot_multiplier": 1.25,
            "effective_shots": 2560.0,
            "transpile_topology": "analytical_statevector",
            "basis_gates": [],
            "routing_method": "sabre",
            "seed_transpiler": 42,
            "execution_billing_mode": "job",
            "calibration_aware_routing": true,
            "mean_mock_cnot_error": 0.0,
            "max_mock_cnot_error": 0.0,
            "estimated_swap_risk_penalty": 0.0,
            "estimated_billed_seconds": 2.005055291003373,
            "estimated_qpu_cost_usd": 0.0
          }
        },
        {
          "evaluation_index": 7,
          "params": [
            3.4114517159908457,
            0.0,
            6.232381416193556,
            0.7905413541930514
          ],
          "objective": -0.40890368829369284,
          "raw_objective": -0.40890368829369284,
          "variance": 0.0012795872829470811,
          "observation_noise_variance": 6.2479847800150446e-06,
          "best_valid_energy": -0.5085661952267606,
          "valid_ratio": 0.326171875,
          "feasible_hit": true,
          "approx_gap": 0.0,
          "timing": {
            "classical_overhead_seconds": 0.09927566700207535,
            "circuit_construction_seconds": 0.0,
            "transpilation_seconds": 0.0,
            "execution_seconds": 0.005034624999098014,
            "mitigation_seconds": 0.000243041999056004,
            "queue_latency_seconds": 2.0,
            "total_seconds": 2.1045533750002505
          },
          "backend_stats": {
            "backend_name": "fast_simulator",
            "initial_state_strategy": "dicke",
            "simulator_seed": null,
            "zne_simulator_seeds": [],
            "transpiled_depth": 0,
            "transpiled_size": 0,
            "two_qubit_gate_count": 0,
            "swap_gate_count": 0,
            "shot_multiplier": 1.25,
            "effective_shots": 2560.0,
            "transpile_topology": "analytical_statevector",
            "basis_gates": [],
            "routing_method": "sabre",
            "seed_transpiler": 42,
            "execution_billing_mode": "job",
            "calibration_aware_routing": true,
            "mean_mock_cnot_error": 0.0,
            "max_mock_cnot_error": 0.0,
            "estimated_swap_risk_penalty": 0.0,
            "estimated_billed_seconds": 2.005277707998175,
            "estimated_qpu_cost_usd": 0.0
          }
        },
        {
          "evaluation_index": 8,
          "params": [
            3.42140457157763,
            0.0,
            6.02199502912188,
            0.7961404394856034
          ],
          "objective": -0.4029616828829722,
          "raw_objective": -0.4029616828829722,
          "variance": 0.0010965083777509654,
          "observation_noise_variance": 5.354044813237136e-06,
          "best_valid_energy": -0.5085661952267606,
          "valid_ratio": 0.32080078125,
          "feasible_hit": true,
          "approx_gap": 0.0,
          "timing": {
            "classical_overhead_seconds": 0.08406137500423938,
            "circuit_construction_seconds": 0.0,
            "transpilation_seconds": 0.0,
            "execution_seconds": 0.004815792002773378,
            "mitigation_seconds": 0.000298250000923872,
            "queue_latency_seconds": 2.0,
            "total_seconds": 2.089175500004785
          },
          "backend_stats": {
            "backend_name": "fast_simulator",
            "initial_state_strategy": "dicke",
            "simulator_seed": null,
            "zne_simulator_seeds": [],
            "transpiled_depth": 0,
            "transpiled_size": 0,
            "two_qubit_gate_count": 0,
            "swap_gate_count": 0,
            "shot_multiplier": 1.25,
            "effective_shots": 2560.0,
            "transpile_topology": "analytical_statevector",
            "basis_gates": [],
            "routing_method": "sabre",
            "seed_transpiler": 42,
            "execution_billing_mode": "job",
            "calibration_aware_routing": true,
            "mean_mock_cnot_error": 0.0,
            "max_mock_cnot_error": 0.0,
            "estimated_swap_risk_penalty": 0.0,
            "estimated_billed_seconds": 2.0051141250005458,
            "estimated_qpu_cost_usd": 0.0
          }
        },
        {
          "evaluation_index": 9,
          "params": [
            3.3454851551445666,
            3.062450049547501,
            0.0,
            1.0909758473460744
          ],
          "objective": -0.40606549542188786,
          "raw_objective": -0.40606549542188786,
          "variance": 0.0013053911538596918,
          "observation_noise_variance": 6.373980243455527e-06,
          "best_valid_energy": -0.5085661952267606,
          "valid_ratio": 0.31298828125,
          "feasible_hit": true,
          "approx_gap": 0.0,
          "timing": {
            "classical_overhead_seconds": 0.08977775100356666,
            "circuit_construction_seconds": 0.0,
            "transpilation_seconds": 0.0,
            "execution_seconds": 0.004760875002830289,
            "mitigation_seconds": 0.00027154100098414347,
            "queue_latency_seconds": 2.0,
            "total_seconds": 2.0948103340051603
          },
          "backend_stats": {
            "backend_name": "fast_simulator",
            "initial_state_strategy": "dicke",
            "simulator_seed": null,
            "zne_simulator_seeds": [],
            "transpiled_depth": 0,
            "transpiled_size": 0,
            "two_qubit_gate_count": 0,
            "swap_gate_count": 0,
            "shot_multiplier": 1.25,
            "effective_shots": 2560.0,
            "transpile_topology": "analytical_statevector",
            "basis_gates": [],
            "routing_method": "sabre",
            "seed_transpiler": 42,
            "execution_billing_mode": "job",
            "calibration_aware_routing": true,
            "mean_mock_cnot_error": 0.0,
            "max_mock_cnot_error": 0.0,
            "estimated_swap_risk_penalty": 0.0,
            "estimated_billed_seconds": 2.0050325830015936,
            "estimated_qpu_cost_usd": 0.0
          }
        },
        {
          "evaluation_index": 10,
          "params": [
            3.339795045607332,
            2.987059512357892,
            0.0,
            1.1649473554028111
          ],
          "objective": -0.41377503363938545,
          "raw_objective": -0.41377503363938545,
          "variance": 0.0010415400374726713,
          "observation_noise_variance": 5.085644714222028e-06,
          "best_valid_energy": -0.5085661952267606,
          "valid_ratio": 0.328125,
          "feasible_hit": true,
          "approx_gap": 0.0,
          "timing": {
            "classical_overhead_seconds": 0.094010040993453,
            "circuit_construction_seconds": 0.0,
            "transpilation_seconds": 0.0,
            "execution_seconds": 0.0047450000056414865,
            "mitigation_seconds": 0.00028649999876506627,
            "queue_latency_seconds": 2.0,
            "total_seconds": 2.099041582994687
          },
          "backend_stats": {
            "backend_name": "fast_simulator",
            "initial_state_strategy": "dicke",
            "simulator_seed": null,
            "zne_simulator_seeds": [],
            "transpiled_depth": 0,
            "transpiled_size": 0,
            "two_qubit_gate_count": 0,
            "swap_gate_count": 0,
            "shot_multiplier": 1.25,
            "effective_shots": 2560.0,
            "transpile_topology": "analytical_statevector",
            "basis_gates": [],
            "routing_method": "sabre",
            "seed_transpiler": 42,
            "execution_billing_mode": "job",
            "calibration_aware_routing": true,
            "mean_mock_cnot_error": 0.0,
            "max_mock_cnot_error": 0.0,
            "estimated_swap_risk_penalty": 0.0,
            "estimated_billed_seconds": 2.005031542001234,
            "estimated_qpu_cost_usd": 0.0
          }
        },
        {
          "evaluation_index": 11,
          "params": [
            3.407360197879898,
            0.0,
            6.069788556633672,
            1.3212880523995028
          ],
          "objective": -0.4426192398847948,
          "raw_objective": -0.4426192398847948,
          "variance": 0.0014250724833118344,
          "observation_noise_variance": 6.958361734921067e-06,
          "best_valid_energy": -0.5085661952267606,
          "valid_ratio": 0.3232421875,
          "feasible_hit": true,
          "approx_gap": 0.0,
          "timing": {
            "classical_overhead_seconds": 0.1093353339965688,
            "circuit_construction_seconds": 0.0,
            "transpilation_seconds": 0.0,
            "execution_seconds": 0.004846834002819378,
            "mitigation_seconds": 0.0003355830049258657,
            "queue_latency_seconds": 2.0,
            "total_seconds": 2.1145178340011626
          },
          "backend_stats": {
            "backend_name": "fast_simulator",
            "initial_state_strategy": "dicke",
            "simulator_seed": null,
            "zne_simulator_seeds": [],
            "transpiled_depth": 0,
            "transpiled_size": 0,
            "two_qubit_gate_count": 0,
            "swap_gate_count": 0,
            "shot_multiplier": 1.25,
            "effective_shots": 2560.0,
            "transpile_topology": "analytical_statevector",
            "basis_gates": [],
            "routing_method": "sabre",
            "seed_transpiler": 42,
            "execution_billing_mode": "job",
            "calibration_aware_routing": true,
            "mean_mock_cnot_error": 0.0,
            "max_mock_cnot_error": 0.0,
            "estimated_swap_risk_penalty": 0.0,
            "estimated_billed_seconds": 2.0051825000045937,
            "estimated_qpu_cost_usd": 0.0
          }
        },
        {
          "evaluation_index": 12,
          "params": [
            3.3360950396383053,
            0.0,
            5.022591005437074,
            1.5990420800596277
          ],
          "objective": -0.39890285143378545,
          "raw_objective": -0.39890285143378545,
          "variance": 0.0009252731458537777,
          "observation_noise_variance": 4.517935282489149e-06,
          "best_valid_energy": -0.5085661952267606,
          "valid_ratio": 0.32421875,
          "feasible_hit": true,
          "approx_gap": 0.0,
          "timing": {
            "classical_overhead_seconds": 0.08214299899555044,
            "circuit_construction_seconds": 0.0,
            "transpilation_seconds": 0.0,
            "execution_seconds": 0.004691791997174732,
            "mitigation_seconds": 0.00027387499721953645,
            "queue_latency_seconds": 2.0,
            "total_seconds": 2.087108707994048
          },
          "backend_stats": {
            "backend_name": "fast_simulator",
            "initial_state_strategy": "dicke",
            "simulator_seed": null,
            "zne_simulator_seeds": [],
            "transpiled_depth": 0,
            "transpiled_size": 0,
            "two_qubit_gate_count": 0,
            "swap_gate_count": 0,
            "shot_multiplier": 1.25,
            "effective_shots": 2560.0,
            "transpile_topology": "analytical_statevector",
            "basis_gates": [],
            "routing_method": "sabre",
            "seed_transpiler": 42,
            "execution_billing_mode": "job",
            "calibration_aware_routing": true,
            "mean_mock_cnot_error": 0.0,
            "max_mock_cnot_error": 0.0,
            "estimated_swap_risk_penalty": 0.0,
            "estimated_billed_seconds": 2.0049657089984976,
            "estimated_qpu_cost_usd": 0.0
          }
        }
      ]
    }
  },
  "single_run_insights": [
    "On regime=baseline, Classical Markowitz achieved the best raw objective (-0.5086) relative to the exact feasible reference (-0.5086).",
    "Feasibility was strongest for Classical Markowitz with feasible-hit rate 100.00% and best valid energy -0.5086."
  ]
}